kiek/__init__.py
kiek/cli.py
kiek/kiek.py
kiek-0.2.5.dist-info/DESCRIPTION.rst
kiek-0.2.5.dist-info/METADATA
kiek-0.2.5.dist-info/RECORD
kiek-0.2.5.dist-info/WHEEL
kiek-0.2.5.dist-info/entry_points.txt
kiek-0.2.5.dist-info/metadata.json
kiek-0.2.5.dist-info/top_level.txt
