Metadata-Version: 2.0
Name: kiek
Version: 0.2.5
Summary: A KISS Kiekshow App
Home-page: https://github.com/maartenq/kiek
Author: Maarten Diemel
Author-email: maarten@maartendiemel.nl
License: ISC license
Keywords: kiek
Platform: UNKNOWN
Classifier: Development Status :: 2 - Pre-Alpha
Classifier: Intended Audience :: Developers
Classifier: License :: OSI Approved :: ISC License (ISCL)
Classifier: Natural Language :: English
Classifier: Programming Language :: Python :: 2
Classifier: Programming Language :: Python :: 2.6
Classifier: Programming Language :: Python :: 2.7
Classifier: Programming Language :: Python :: 3
Classifier: Programming Language :: Python :: 3.3
Classifier: Programming Language :: Python :: 3.4
Classifier: Programming Language :: Python :: 3.5
Requires-Dist: Click (>=6.0)
